LICENSE
README.md
setup.py
CVE_2023_46805.egg-info/PKG-INFO
CVE_2023_46805.egg-info/SOURCES.txt
CVE_2023_46805.egg-info/dependency_links.txt
CVE_2023_46805.egg-info/entry_points.txt
CVE_2023_46805.egg-info/requires.txt
CVE_2023_46805.egg-info/top_level.txt
cve202346805/__init__.py
cve202346805/main.py
cve202346805/includes/__init__.py
cve202346805/includes/bot.py
cve202346805/includes/filereader.py
cve202346805/includes/scan.py
cve202346805/includes/writefile.py
cve202346805/utils/__init__.py
cve202346805/utils/configure.py
cve202346805/utils/const.py
cve202346805/utils/helpers.py
cve202346805/utils/status.py